LICENSE
MANIFEST.in
README.md
requirements.txt
setup.py
hertz_studio_django_captcha/__init__.py
hertz_studio_django_captcha/api_views.py
hertz_studio_django_captcha/apps.py
hertz_studio_django_captcha/captcha_generator.py
hertz_studio_django_captcha/models.py
hertz_studio_django_captcha/serializers.py
hertz_studio_django_captcha/tests.py
hertz_studio_django_captcha/urls.py
hertz_studio_django_captcha.egg-info/PKG-INFO
hertz_studio_django_captcha.egg-info/SOURCES.txt
hertz_studio_django_captcha.egg-info/dependency_links.txt
hertz_studio_django_captcha.egg-info/requires.txt
hertz_studio_django_captcha.egg-info/top_level.txt
hertz_studio_django_captcha/migrations/__init__.py