Metadata-Version: 2.4
Name: hertz_studio_django_captcha
Version: 1.0.2
Summary: 一个功能强大的Django验证码应用
Home-page: http://hzgit.hzsystems.cn/hertz_studio_django/hertz_studio_django_captcha
Author: yang kunhao
Author-email: 563161210@qq.com
License: MIT
Project-URL: Bug Reports, http://hzgit.hzsystems.cn/hertz_studio_django/hertz_studio_django_captcha/issues
Project-URL: Source, http://hzgit.hzsystems.cn/hertz_studio_django/hertz_studio_django_captcha
Project-URL: Documentation, http://hzgit.hzsystems.cn/hertz_studio_django/hertz_studio_django_captcha#readme
Keywords: django captcha verification security
Classifier: Development Status :: 4 - Beta
Classifier: Intended Audience :: Developers
Classifier: Operating System :: OS Independent
Classifier: Framework :: Django
Classifier: Framework :: Django :: 3.0
Classifier: Framework :: Django :: 3.1
Classifier: Framework :: Django :: 3.2
Classifier: Framework :: Django :: 4.0
Classifier: Framework :: Django :: 4.1
Classifier: Framework :: Django :: 4.2
Classifier: Programming Language :: Python
Classifier: Programming Language :: Python :: 3
Classifier: Programming Language :: Python :: 3.7
Classifier: Programming Language :: Python :: 3.8
Classifier: Programming Language :: Python :: 3.9
Classifier: Programming Language :: Python :: 3.10
Classifier: Programming Language :: Python :: 3.11
Classifier: Topic :: Internet :: WWW/HTTP
Classifier: Topic :: Software Development :: Libraries :: Python Modules
Requires-Python: >=3.10
License-File: LICENSE
Requires-Dist: Django>=5.0
Requires-Dist: Pillow>=10.0.0
Requires-Dist: redis>=5.0
Requires-Dist: django-redis>=5.0
Requires-Dist: requests>=2.25.0
Dynamic: author
Dynamic: author-email
Dynamic: classifier
Dynamic: description
Dynamic: description-content-type
Dynamic: home-page
Dynamic: keywords
Dynamic: license
Dynamic: license-file
Dynamic: project-url
Dynamic: requires-dist
Dynamic: requires-python
Dynamic: summary
